MANIFEST.in
README.rst
setup.py
argpar/__init__.py
argpar.egg-info/PKG-INFO
argpar.egg-info/SOURCES.txt
argpar.egg-info/dependency_links.txt
argpar.egg-info/not-zip-safe
argpar.egg-info/top_level.txt