Metadata-Version: 1.0
Name: argpar
Version: 1.2.0
Summary: A simple arugments parser.
Home-page: https://github.com/ondra6ak/argpar.git
Author: Ondrej Sestak
Author-email: ondra6ak@gmail.com
License: BSD
Platform: UNKNOWN
